ailab/__init__.py
ailab/atp_dataset/__init__.py
ailab/atp_dataset/ailab_api.py
ailab/atp_dataset/constant.py
ailab/atp_dataset/dataset.py
ailab/atp_dataset/huggingface_api.py
ailab/atp_dataset/modelscope_api.py
ailab/atp_finetuner/__init__.py
ailab/atp_finetuner/accelerator/__init__.py
ailab/atp_finetuner/accelerator/accelerator.py
ailab/atp_finetuner/build.py
ailab/atp_finetuner/constant.py
ailab/atp_finetuner/datacollator/__init__.py
ailab/atp_finetuner/datacollator/datacollator.py
ailab/atp_finetuner/datacollator/dc_for_alpaca.py
ailab/atp_finetuner/datacollator/dc_for_chatglm.py
ailab/atp_finetuner/datacollator/dc_for_language.py
ailab/atp_finetuner/datacollator/dc_for_token.py
ailab/atp_finetuner/datacollator/dc_with_padding.py
ailab/atp_finetuner/finetuner.py
ailab/atp_finetuner/metric/__init__.py
ailab/atp_finetuner/metric/accury.py
ailab/atp_finetuner/metric/metric.py
ailab/atp_finetuner/model/__init__.py
ailab/atp_finetuner/model/cv/__init__.py
ailab/atp_finetuner/model/model.py
ailab/atp_finetuner/model/multimodel/__init__.py
ailab/atp_finetuner/model/multimodel/model_for_sd_lora.py
ailab/atp_finetuner/model/multimodel/vilt_for_vqa.py
ailab/atp_finetuner/model/nlp/__init__.py
ailab/atp_finetuner/model/nlp/model_for_chatglm.py
ailab/atp_finetuner/model/nlp/model_for_lora.py
ailab/atp_finetuner/model/nlp/model_for_question_answer.py
ailab/atp_finetuner/model/nlp/model_for_text_classification.py
ailab/atp_finetuner/model/nlp/model_for_token_classification.py
ailab/atp_finetuner/preprossor/__init__.py
ailab/atp_finetuner/preprossor/cv/__init__.py
ailab/atp_finetuner/preprossor/multimodel/__init__.py
ailab/atp_finetuner/preprossor/multimodel/pc_for_sd_lora.py
ailab/atp_finetuner/preprossor/multimodel/pc_for_vilt_vqa.py
ailab/atp_finetuner/preprossor/nlp/__init__.py
ailab/atp_finetuner/preprossor/nlp/pc_for_alpaca.py
ailab/atp_finetuner/preprossor/nlp/pc_for_chatglm.py
ailab/atp_finetuner/preprossor/nlp/pc_for_llama_cn.py
ifly_ailab-1.0.0.dist-info/LICENSE
ifly_ailab-1.0.0.dist-info/METADATA
ifly_ailab-1.0.0.dist-info/WHEEL
ifly_ailab-1.0.0.dist-info/RECORD
