Metadata-Version: 2.1
Name: ifly-ailab
Version: 1.0.0
Summary: a iflytek ailab library ...
License: Apache License 2
Author: mjchen
Author-email: mjchen@iflytek.com
Requires-Python: >3.7
Classifier: License :: Other/Proprietary License
Classifier: Programming Language :: Python :: 3
Classifier: Programming Language :: Python :: 3.8
Classifier: Programming Language :: Python :: 3.9
Classifier: Programming Language :: Python :: 3.10
Classifier: Programming Language :: Python :: 3.11
Requires-Dist: SentencePiece
Requires-Dist: accelerate
Requires-Dist: bitsandbytes
Requires-Dist: cpm_kernels
Requires-Dist: datasets
Requires-Dist: evaluate
Requires-Dist: giteapy
Requires-Dist: modelscope
Requires-Dist: requests
Requires-Dist: scikit-learn
Requires-Dist: tensorboard
Requires-Dist: torch
Requires-Dist: torchvision
Requires-Dist: transformers
